setup.cfg
setup.py
osimis_logging/__init__.py
osimis_logging/logHelpers.py
osimis_logging.egg-info/PKG-INFO
osimis_logging.egg-info/SOURCES.txt
osimis_logging.egg-info/dependency_links.txt
osimis_logging.egg-info/top_level.txt