Metadata-Version: 1.0
Name: osimis-logging
Version: 0.1.0
Summary: Extended logging classes.
Home-page: https://bitbucket.org/osimis/python-osimis-logging
Author: Alain Mazy
Author-email: am@osimis.io
License: UNKNOWN
Keywords: LogHelpers,logging
Platform: UNKNOWN
